color_tools/__init__.py
color_tools/color.py
color_tools-0.0.2.dist-info/LICENSE
color_tools-0.0.2.dist-info/METADATA
color_tools-0.0.2.dist-info/WHEEL
color_tools-0.0.2.dist-info/top_level.txt
color_tools-0.0.2.dist-info/RECORD
